{
  "children": {
    "fragment": [
      {
        "type": "abstract",
        "doi": "10.7554/eLife.05462.001",
        "path": "content/4/e05462/abstract-1"
      },
      {
        "type": "abstract",
        "doi": "10.7554/eLife.05462.002",
        "path": "content/4/e05462/abstract-2",
        "abstract-type": "executive-summary"
      },
      {
        "type": "fig",
        "doi": "10.7554/eLife.05462.003",
        "path": "content/4/e05462/F1",
        "title": "Figure 1."
      },
      {
        "type": "fig",
        "doi": "10.7554/eLife.05462.004",
        "path": "content/4/e05462/F2",
        "title": "Figure 2."
      },
      {
        "type": "fig",
        "doi": "10.7554/eLife.05462.005",
        "path": "content/4/e05462/F3",
        "title": "Figure 3."
      },
      {
        "type": "fig",
        "doi": "10.7554/eLife.05462.006",
        "path": "content/4/e05462/F4",
        "title": "Figure 4."
      },
      {
        "type": "fig",
        "doi": "10.7554/eLife.05462.007",
        "path": "content/4/e05462/F5",
        "title": "Figure 5."
      },
      {
        "type": "fig",
        "doi": "10.7554/eLife.05462.008",
        "path": "content/4/e05462/F6",
        "title": "Figure 6."
      },
      {
        "type": "table-wrap",
        "doi": "10.7554/eLife.05462.009",
        "path": "content/4/e05462/T1",
        "title": "Table 1."
      },
      {
        "type": "fig",
        "doi": "10.7554/eLife.05462.010",
        "path": "content/4/e05462/F7",
        "title": "Figure 7."
      },
      {
        "type": "fig",
        "doi": "10.7554/eLife.05462.011",
        "path": "content/4/e05462/F8",
        "title": "Figure 8."
      },
      {
        "type": "fig",
        "doi": "10.7554/eLife.05462.012",
        "path": "content/4/e05462/F9",
        "title": "Figure 9."
      },
      {
        "type": "fig",
        "doi": "10.7554/eLife.05462.013",
        "path": "content/4/e05462/F10",
        "title": "Figure 10."
      },
      {
        "type": "supplementary-material",
        "doi": "10.7554/eLife.05462.014",
        "path": "content/4/e05462/DC1",
        "title": "Supplementary file 1."
      },
      {
        "type": "supplementary-material",
        "doi": "10.7554/eLife.05462.015",
        "path": "content/4/e05462/DC2",
        "title": "Supplementary file 2."
      },
      {
        "type": "supplementary-material",
        "doi": "10.7554/eLife.05462.016",
        "path": "content/4/e05462/DC3",
        "title": "Supplementary file 3."
      },
      {
        "type": "fig",
        "doi": "10.7554/eLife.05462.017",
        "path": "content/4/e05462/F11",
        "title": "Appendix 1 Figure 1."
      }
    ],
    "sub-article": [
      {
        "doi": "10.7554/eLife.05462.018",
        "path": "content/4/e05462/1",
        "title": "Decision letter"
      },
      {
        "doi": "10.7554/eLife.05462.019",
        "path": "content/4/e05462/2",
        "title": "Author response"
      }
    ]
  }
}